README
setup.py
revtrans/__init__.py
revtrans/mod_seqfiles.py
revtrans/mod_translate.py
revtrans/ncbi_genetic_codes.py
revtrans.egg-info/PKG-INFO
revtrans.egg-info/SOURCES.txt
revtrans.egg-info/dependency_links.txt
revtrans.egg-info/entry_points.txt
revtrans.egg-info/top_level.txt