Metadata-Version: 1.0
Name: revtrans
Version: 1.4
Summary: revtrans - performs a reverse translation of a peptide alignment
Home-page: http://pypi.python.org/pypi/revtrans
Author: Rasmus Wernersson
Author-email: UNKNOWN
License: GNU General Public License 2
Platform: UNKNOWN
